Metadata-Version: 2.1
Name: MAgIC-LLM
Version: 0.8.0
Summary: MAgIC: Investigation of Large Language Model Powered Multi-Agent in Cognition, Adaptability, Rationality and Collaboration
Home-page: https://zhiyuanhubj.github.io/MAgIC/
Author: Zhiyuan Hu
Author-email: Zhiyuan Hu <zhiyuan.hu.bj@gmail.com>
License: UNKNOWN
Project-URL: Homepage, https://zhiyuanhubj.github.io/MAgIC/
Project-URL: Bug Tracker, https://github.com/cathyxl/MAgIC/issues
Platform: UNKNOWN
Classifier: Programming Language :: Python :: 3
Classifier: License :: OSI Approved :: MIT License
Classifier: Operating System :: OS Independent
Requires-Python: >=3.7
Provides-Extra: all_backends
Provides-Extra: all
Provides-Extra: anthropic
Provides-Extra: cohere
Provides-Extra: huggingface
Provides-Extra: bard
Provides-Extra: langchain
Provides-Extra: gradio
Provides-Extra: pettingzoo
Provides-Extra: umshini
Provides-Extra: all_envs
License-File: LICENSE
